rest_framework_actions/__init__.py
rest_framework_actions/apps.py
rest_framework_actions/mixins.py
rest_framework_actions/tests.py
rest_framework_actions/viewsets.py
rest_framework_actions/migrations/__init__.py
rest_framework_actions-0.1.dist-info/LICENSE
rest_framework_actions-0.1.dist-info/METADATA
rest_framework_actions-0.1.dist-info/WHEEL
rest_framework_actions-0.1.dist-info/top_level.txt
rest_framework_actions-0.1.dist-info/RECORD
